setup.py
mediaflow/__init__.py
mediaflow/config.py
mediaflow/data.py
mediaflow/decorator.py
mediaflow/function_base.py
mediaflow/function_data.py
mediaflow/local_run.py
mediaflow.egg-info/PKG-INFO
mediaflow.egg-info/SOURCES.txt
mediaflow.egg-info/dependency_links.txt
mediaflow.egg-info/entry_points.txt
mediaflow.egg-info/requires.txt
mediaflow.egg-info/top_level.txt
mediaflow/jar/javawrapper-1.0.2-SNAPSHOT-jar-with-dependencies.jar
mediaflow/ops/__init__.py