Metadata-Version: 2.1
Name: mediaflow
Version: 0.0.1
Summary: media streaming engine.
Home-page: UNKNOWN
Author: wingo.zwt
Author-email: wingo.zwt@alibaba-inc.com
License: BSD
Download-URL: http://eas-public.oss-cn-hangzhou-zmf.aliyuncs.com/pkg/
Keywords: mediaflow
Platform: UNKNOWN
